{
  "#acknowledgments": {
    "current": {
      "number": "", 
      "spec": "CSS Scrollbars", 
      "text": "Acknowledgments", 
      "url": "https://drafts.csswg.org/css-scrollbars-1/#acknowledgments"
    }, 
    "snapshot": {
      "number": "", 
      "spec": "CSS Scrollbars", 
      "text": "Acknowledgments", 
      "url": "https://www.w3.org/TR/css-scrollbars-1/#acknowledgments"
    }
  }, 
  "#changes": {
    "current": {
      "number": "", 
      "spec": "CSS Scrollbars", 
      "text": "Changes", 
      "url": "https://drafts.csswg.org/css-scrollbars-1/#changes"
    }, 
    "snapshot": {
      "number": "", 
      "spec": "CSS Scrollbars", 
      "text": "Changes", 
      "url": "https://www.w3.org/TR/css-scrollbars-1/#changes"
    }
  }, 
  "#intro": {
    "current": {
      "number": "1", 
      "spec": "CSS Scrollbars", 
      "text": "Introduction", 
      "url": "https://drafts.csswg.org/css-scrollbars-1/#intro"
    }, 
    "snapshot": {
      "number": "1", 
      "spec": "CSS Scrollbars", 
      "text": "Introduction", 
      "url": "https://www.w3.org/TR/css-scrollbars-1/#intro"
    }
  }, 
  "#scope": {
    "current": {
      "number": "1.1", 
      "spec": "CSS Scrollbars", 
      "text": "Scope", 
      "url": "https://drafts.csswg.org/css-scrollbars-1/#scope"
    }, 
    "snapshot": {
      "number": "1.1", 
      "spec": "CSS Scrollbars", 
      "text": "Scope", 
      "url": "https://www.w3.org/TR/css-scrollbars-1/#scope"
    }
  }, 
  "#scrollbar-color": {
    "current": {
      "number": "2", 
      "spec": "CSS Scrollbars", 
      "text": "Scrollbar Colors: the scrollbar-color property", 
      "url": "https://drafts.csswg.org/css-scrollbars-1/#scrollbar-color"
    }, 
    "snapshot": {
      "number": "2", 
      "spec": "CSS Scrollbars", 
      "text": "Scrollbar Colors: the scrollbar-color property", 
      "url": "https://www.w3.org/TR/css-scrollbars-1/#scrollbar-color"
    }
  }, 
  "#scrollbar-width": {
    "current": {
      "number": "3", 
      "spec": "CSS Scrollbars", 
      "text": "Scrollbar Thickness: the scrollbar-width property", 
      "url": "https://drafts.csswg.org/css-scrollbars-1/#scrollbar-width"
    }, 
    "snapshot": {
      "number": "3", 
      "spec": "CSS Scrollbars", 
      "text": "Scrollbar Thickness: the scrollbar-width property", 
      "url": "https://www.w3.org/TR/css-scrollbars-1/#scrollbar-width"
    }
  }, 
  "#security-privacy-considerations": {
    "current": {
      "number": "", 
      "spec": "CSS Scrollbars", 
      "text": "Considerations for Security and Privacy", 
      "url": "https://drafts.csswg.org/css-scrollbars-1/#security-privacy-considerations"
    }, 
    "snapshot": {
      "number": "", 
      "spec": "CSS Scrollbars", 
      "text": "Considerations for Security and Privacy", 
      "url": "https://www.w3.org/TR/css-scrollbars-1/#security-privacy-considerations"
    }
  }, 
  "#values": {
    "current": {
      "number": "1.2", 
      "spec": "CSS Scrollbars", 
      "text": "Values", 
      "url": "https://drafts.csswg.org/css-scrollbars-1/#values"
    }, 
    "snapshot": {
      "number": "1.2", 
      "spec": "CSS Scrollbars", 
      "text": "Values", 
      "url": "https://www.w3.org/TR/css-scrollbars-1/#values"
    }
  }
}