{
  "#DataTypes": {
    "current": {
      "number": "3.1", 
      "spec": "WOFF 2.0", 
      "text": "Data types", 
      "url": "https://dev.w3.org/webfonts/WOFF2/spec/#DataTypes"
    }
  }, 
  "#FileStructure": {
    "current": {
      "number": "3", 
      "spec": "WOFF 2.0", 
      "text": "Overall file structure and basic data types", 
      "url": "https://dev.w3.org/webfonts/WOFF2/spec/#FileStructure"
    }
  }, 
  "#General": {
    "current": {
      "number": "2", 
      "spec": "WOFF 2.0", 
      "text": "General Requirements", 
      "url": "https://dev.w3.org/webfonts/WOFF2/spec/#General"
    }
  }, 
  "#IMT": {
    "current": {
      "number": "", 
      "spec": "WOFF 2.0", 
      "text": "Internet Media Type Registration", 
      "url": "https://dev.w3.org/webfonts/WOFF2/spec/#IMT"
    }
  }, 
  "#Introduction": {
    "current": {
      "number": "1", 
      "spec": "WOFF 2.0", 
      "text": "Introduction", 
      "url": "https://dev.w3.org/webfonts/WOFF2/spec/#Introduction"
    }
  }, 
  "#Metadata": {
    "current": {
      "number": "6", 
      "spec": "WOFF 2.0", 
      "text": "Extended Metadata Block", 
      "url": "https://dev.w3.org/webfonts/WOFF2/spec/#Metadata"
    }
  }, 
  "#Notation": {
    "current": {
      "number": "1.1", 
      "spec": "WOFF 2.0", 
      "text": "Notational Conventions", 
      "url": "https://dev.w3.org/webfonts/WOFF2/spec/#Notation"
    }
  }, 
  "#Private": {
    "current": {
      "number": "7", 
      "spec": "WOFF 2.0", 
      "text": "Private Data Block", 
      "url": "https://dev.w3.org/webfonts/WOFF2/spec/#Private"
    }
  }, 
  "#changes": {
    "current": {
      "number": "", 
      "spec": "WOFF 2.0", 
      "text": "Changes", 
      "url": "https://dev.w3.org/webfonts/WOFF2/spec/#changes"
    }
  }, 
  "#collection_dir_format": {
    "current": {
      "number": "4.2", 
      "spec": "WOFF 2.0", 
      "text": "Collection directory format", 
      "url": "https://dev.w3.org/webfonts/WOFF2/spec/#collection_dir_format"
    }
  }, 
  "#font_directory": {
    "current": {
      "number": "4", 
      "spec": "WOFF 2.0", 
      "text": "Font directory", 
      "url": "https://dev.w3.org/webfonts/WOFF2/spec/#font_directory"
    }
  }, 
  "#glyf_table_format": {
    "current": {
      "number": "5.1", 
      "spec": "WOFF 2.0", 
      "text": "Transformed glyf table format", 
      "url": "https://dev.w3.org/webfonts/WOFF2/spec/#glyf_table_format"
    }
  }, 
  "#hmtx_table_format": {
    "current": {
      "number": "5.4", 
      "spec": "WOFF 2.0", 
      "text": "Transformed hmtx table format", 
      "url": "https://dev.w3.org/webfonts/WOFF2/spec/#hmtx_table_format"
    }
  }, 
  "#loca_table_format": {
    "current": {
      "number": "5.3", 
      "spec": "WOFF 2.0", 
      "text": "Transformed loca table format", 
      "url": "https://dev.w3.org/webfonts/WOFF2/spec/#loca_table_format"
    }
  }, 
  "#security-privacy-considerations": {
    "current": {
      "number": "", 
      "spec": "WOFF 2.0", 
      "text": "Considerations for Security and Privacy", 
      "url": "https://dev.w3.org/webfonts/WOFF2/spec/#security-privacy-considerations"
    }
  }, 
  "#table_dir_format": {
    "current": {
      "number": "4.1", 
      "spec": "WOFF 2.0", 
      "text": "Table directory format", 
      "url": "https://dev.w3.org/webfonts/WOFF2/spec/#table_dir_format"
    }
  }, 
  "#table_format": {
    "current": {
      "number": "5", 
      "spec": "WOFF 2.0", 
      "text": "Compressed data format", 
      "url": "https://dev.w3.org/webfonts/WOFF2/spec/#table_format"
    }
  }, 
  "#table_order": {
    "current": {
      "number": "5.5", 
      "spec": "WOFF 2.0", 
      "text": "Table order constraints", 
      "url": "https://dev.w3.org/webfonts/WOFF2/spec/#table_order"
    }
  }, 
  "#triplet_decoding": {
    "current": {
      "number": "5.2", 
      "spec": "WOFF 2.0", 
      "text": "Decoding of variable-length X and Y coordinates", 
      "url": "https://dev.w3.org/webfonts/WOFF2/spec/#triplet_decoding"
    }
  }, 
  "#woff20Header": {
    "current": {
      "number": "3.2", 
      "spec": "WOFF 2.0", 
      "text": "WOFF2 Header", 
      "url": "https://dev.w3.org/webfonts/WOFF2/spec/#woff20Header"
    }
  }
}