{
 "notes": "Firefox OS is reported to have partial support for this property as `x-inputmode`.\r\n\r\nBlink-based browsers appear to recognize the `inputMode` property on `input` & `textarea` fields though it is unclear what effect it currently has as the feature is still in development.", 
 "support": {
  "Android Browser": "y 67", 
  "Baidu Browser": "n 7.12", 
  "Blackberry Browser": "n 10", 
  "Chrome": "y 66", 
  "Chrome for Android": "y 74", 
  "Edge": "y 75", 
  "Firefox": "n 69", 
  "Firefox for Android": "n 66", 
  "IE": "n 11", 
  "IE Mobile": "n 11", 
  "KaiOS Browser": "n 2.5", 
  "Opera": "y 53", 
  "Opera Mini": "n all", 
  "Opera Mobile": "n 46", 
  "QQ Browser": "n 1.2", 
  "Safari": "n TP", 
  "Samsung Internet": "y 9.2", 
  "UC Browser for Android": "n 11.8", 
  "iOS Safari": "y 12.2"
 }, 
 "url": "https://html.spec.whatwg.org/multipage/forms.html#input-modalities:-the-inputmode-attribute"
}