{
    "dom-mediametadata-mediametadata": [
        {
            "engines": [
                "blink",
                "gecko"
            ],
            "filename": "api/MediaMetadata.json",
            "name": "MediaMetadata",
            "slug": "API/MediaMetadata/MediaMetadata",
            "summary": "The MediaMetadata() constructor creates a new MediaMetadata object.",
            "support": {
                "chrome": {
                    "version_added": "57"
                },
                "chrome_android": {
                    "version_added": "57"
                },
                "edge": {
                    "version_added": false
                },
                "firefox": {
                    "version_added": "71"
                },
                "firefox_android": {
                    "version_added": "82"
                },
                "ie": {
                    "version_added": false
                },
                "opera": {
                    "version_added": true
                },
                "opera_android": {
                    "version_added": false
                },
                "safari": {
                    "version_added": false
                },
                "safari_ios": {
                    "version_added": false
                },
                "samsunginternet_android": {
                    "version_added": "7.0"
                },
                "webview_android": {
                    "version_added": false
                },
                "edge_blink": {
                    "version_added": "79"
                }
            },
            "title": "MediaMetadata.MediaMetadata()"
        }
    ],
    "dom-mediametadata-album": [
        {
            "engines": [
                "blink",
                "gecko"
            ],
            "filename": "api/MediaMetadata.json",
            "name": "album",
            "slug": "API/MediaMetadata/album",
            "summary": "The album property of the MediaMetaData interface returns or sets the name of the album or collection containing the media to be played.",
            "support": {
                "chrome": {
                    "version_added": "57"
                },
                "chrome_android": {
                    "version_added": "57"
                },
                "edge": {
                    "version_added": false
                },
                "firefox": {
                    "version_added": "71"
                },
                "firefox_android": {
                    "version_added": "82"
                },
                "ie": {
                    "version_added": false
                },
                "opera": {
                    "version_added": true
                },
                "opera_android": {
                    "version_added": false
                },
                "safari": {
                    "version_added": false
                },
                "safari_ios": {
                    "version_added": false
                },
                "samsunginternet_android": {
                    "version_added": "7.0"
                },
                "webview_android": {
                    "version_added": false
                },
                "edge_blink": {
                    "version_added": "79"
                }
            },
            "title": "MediaMetadata.album"
        }
    ],
    "dom-mediametadata-artist": [
        {
            "engines": [
                "blink",
                "gecko"
            ],
            "filename": "api/MediaMetadata.json",
            "name": "artist",
            "slug": "API/MediaMetadata/artist",
            "summary": "The artist property of the MediaMetaData interface returns or sets the name of the artist, group, creator, etc., of the media to be played.",
            "support": {
                "chrome": {
                    "version_added": "57"
                },
                "chrome_android": {
                    "version_added": "57"
                },
                "edge": {
                    "version_added": false
                },
                "firefox": {
                    "version_added": "71"
                },
                "firefox_android": {
                    "version_added": "82"
                },
                "ie": {
                    "version_added": false
                },
                "opera": {
                    "version_added": true
                },
                "opera_android": {
                    "version_added": false
                },
                "safari": {
                    "version_added": false
                },
                "safari_ios": {
                    "version_added": false
                },
                "samsunginternet_android": {
                    "version_added": "7.0"
                },
                "webview_android": {
                    "version_added": false
                },
                "edge_blink": {
                    "version_added": "79"
                }
            },
            "title": "MediaMetadata.artist"
        }
    ],
    "dom-mediametadata-artwork": [
        {
            "engines": [
                "blink",
                "gecko"
            ],
            "filename": "api/MediaMetadata.json",
            "name": "artwork",
            "slug": "API/MediaMetadata/artwork",
            "summary": "The artwork property of the MediaMetaData interface returns or sets an array of MediaImage objects representing images associated with playing media.",
            "support": {
                "chrome": {
                    "version_added": "57"
                },
                "chrome_android": {
                    "version_added": "57"
                },
                "edge": {
                    "version_added": false
                },
                "firefox": {
                    "version_added": "71"
                },
                "firefox_android": {
                    "version_added": "82"
                },
                "ie": {
                    "version_added": false
                },
                "opera": {
                    "version_added": true
                },
                "opera_android": {
                    "version_added": false
                },
                "safari": {
                    "version_added": false
                },
                "safari_ios": {
                    "version_added": false
                },
                "samsunginternet_android": {
                    "version_added": "7.0"
                },
                "webview_android": {
                    "version_added": false
                },
                "edge_blink": {
                    "version_added": "79"
                }
            },
            "title": "MediaMetadata.artwork"
        }
    ],
    "dom-mediametadata-title": [
        {
            "engines": [
                "blink",
                "gecko"
            ],
            "filename": "api/MediaMetadata.json",
            "name": "title",
            "slug": "API/MediaMetadata/title",
            "summary": "The title property of the MediaMetaData interface returns or sets the title of the media to be played.",
            "support": {
                "chrome": {
                    "version_added": "57"
                },
                "chrome_android": {
                    "version_added": "57"
                },
                "edge": {
                    "version_added": false
                },
                "firefox": {
                    "version_added": "71"
                },
                "firefox_android": {
                    "version_added": "82"
                },
                "ie": {
                    "version_added": false
                },
                "opera": {
                    "version_added": true
                },
                "opera_android": {
                    "version_added": false
                },
                "safari": {
                    "version_added": false
                },
                "safari_ios": {
                    "version_added": false
                },
                "samsunginternet_android": {
                    "version_added": "7.0"
                },
                "webview_android": {
                    "version_added": false
                },
                "edge_blink": {
                    "version_added": "79"
                }
            },
            "title": "MediaMetadata.title"
        }
    ],
    "the-mediametadata-interface": [
        {
            "engines": [
                "blink",
                "gecko"
            ],
            "partial": [
                "gecko"
            ],
            "filename": "api/MediaMetadata.json",
            "name": "MediaMetadata",
            "slug": "API/MediaMetadata",
            "summary": "The MediaMetadata interface of the the Media Session API allows a web page to provide rich media metadata for display in a platform UI.",
            "support": {
                "chrome": {
                    "version_added": "57"
                },
                "chrome_android": {
                    "version_added": "57"
                },
                "edge": {
                    "version_added": false
                },
                "firefox": [
                    {
                        "version_added": "82"
                    },
                    {
                        "version_added": "71",
                        "flags": [
                            {
                                "type": "preference",
                                "name": "dom.media.mediasession.enabled",
                                "value_to_set": "true"
                            }
                        ]
                    }
                ],
                "firefox_android": {
                    "version_added": "82",
                    "partial_implementation": true,
                    "notes": "Firefox exposes the API, but does not provide a corresponding user-facing media control interface."
                },
                "ie": {
                    "version_added": false
                },
                "opera": {
                    "version_added": true
                },
                "opera_android": {
                    "version_added": false
                },
                "safari": {
                    "version_added": false
                },
                "safari_ios": {
                    "version_added": false
                },
                "samsunginternet_android": {
                    "version_added": "7.0"
                },
                "webview_android": {
                    "version_added": false
                },
                "edge_blink": {
                    "version_added": "79"
                }
            },
            "title": "MediaMetadata"
        }
    ],
    "dom-mediasession-metadata": [
        {
            "engines": [
                "blink",
                "gecko"
            ],
            "partial": [
                "gecko"
            ],
            "filename": "api/MediaSession.json",
            "name": "metadata",
            "slug": "API/MediaSession/metadata",
            "summary": "The metadata property of the MediaSession interface contains a MediaMetadata object  providing descriptive information about the currently playing media, or null if the metadata has not been set. This metadata is provided by the browser to the device for presentation in any standard media control user interface the device might offer.",
            "support": {
                "chrome": {
                    "version_added": "73"
                },
                "chrome_android": {
                    "version_added": "57"
                },
                "edge": {
                    "version_added": false
                },
                "firefox": [
                    {
                        "version_added": "82"
                    },
                    {
                        "version_added": "71",
                        "flags": [
                            {
                                "type": "preference",
                                "name": "dom.media.mediasession.enabled",
                                "value_to_set": "true"
                            }
                        ]
                    }
                ],
                "firefox_android": {
                    "version_added": "82",
                    "partial_implementation": true,
                    "notes": "Firefox exposes the API, but does not provide a corresponding user-facing media control interface."
                },
                "ie": {
                    "version_added": false
                },
                "opera": {
                    "version_added": true
                },
                "opera_android": {
                    "version_added": false
                },
                "safari": {
                    "version_added": false
                },
                "safari_ios": {
                    "version_added": false
                },
                "samsunginternet_android": {
                    "version_added": "7.0"
                },
                "webview_android": {
                    "version_added": false
                },
                "edge_blink": {
                    "version_added": "79"
                }
            },
            "title": "MediaSession.metadata"
        }
    ],
    "dom-mediasession-playbackstate": [
        {
            "engines": [
                "blink",
                "gecko"
            ],
            "partial": [
                "gecko"
            ],
            "filename": "api/MediaSession.json",
            "name": "playbackState",
            "slug": "API/MediaSession/playbackState",
            "summary": "The playbackState property of the MediaSession interface indicates whether the current media session is playing or paused.",
            "support": {
                "chrome": {
                    "version_added": "73"
                },
                "chrome_android": {
                    "version_added": "57"
                },
                "edge": {
                    "version_added": false
                },
                "firefox": [
                    {
                        "version_added": "82"
                    },
                    {
                        "version_added": "71",
                        "flags": [
                            {
                                "type": "preference",
                                "name": "dom.media.mediasession.enabled",
                                "value_to_set": "true"
                            }
                        ]
                    }
                ],
                "firefox_android": {
                    "version_added": "82",
                    "partial_implementation": true,
                    "notes": "Firefox exposes the API, but does not provide a corresponding user-facing media control interface."
                },
                "ie": {
                    "version_added": false
                },
                "opera": {
                    "version_added": true
                },
                "opera_android": {
                    "version_added": false
                },
                "safari": {
                    "version_added": false
                },
                "safari_ios": {
                    "version_added": false
                },
                "samsunginternet_android": {
                    "version_added": "7.0"
                },
                "webview_android": {
                    "version_added": false
                },
                "edge_blink": {
                    "version_added": "79"
                }
            },
            "title": "MediaSession.playbackState"
        }
    ],
    "dom-mediasession-setactionhandler": [
        {
            "engines": [
                "blink",
                "gecko"
            ],
            "partial": [
                "gecko"
            ],
            "filename": "api/MediaSession.json",
            "name": "setActionHandler",
            "slug": "API/MediaSession/setActionHandler",
            "summary": "The setActionHandler() method of the MediaSession interface sets a handler for a media session action. These actions let a web app receive notifications when the user engages a device's built-in physical or onscreen media controls, such as play, stop, or seek buttons.",
            "support": {
                "chrome": {
                    "version_added": "73"
                },
                "chrome_android": {
                    "version_added": "57"
                },
                "edge": {
                    "version_added": false
                },
                "firefox": [
                    {
                        "version_added": "82"
                    },
                    {
                        "version_added": "71",
                        "flags": [
                            {
                                "type": "preference",
                                "name": "dom.media.mediasession.enabled",
                                "value_to_set": "true"
                            }
                        ]
                    }
                ],
                "firefox_android": {
                    "version_added": "82",
                    "partial_implementation": true,
                    "notes": "Firefox exposes the API, but does not provide a corresponding user-facing media control interface."
                },
                "ie": {
                    "version_added": false
                },
                "opera": {
                    "version_added": true
                },
                "opera_android": {
                    "version_added": false
                },
                "safari": {
                    "version_added": false
                },
                "safari_ios": {
                    "version_added": false
                },
                "samsunginternet_android": {
                    "version_added": "7.0"
                },
                "webview_android": {
                    "version_added": false
                },
                "edge_blink": {
                    "version_added": "79"
                }
            },
            "title": "MediaSession.setActionHandler()"
        }
    ],
    "dom-mediasession-setpositionstate": [
        {
            "engines": [
                "blink",
                "gecko"
            ],
            "partial": [
                "gecko"
            ],
            "filename": "api/MediaSession.json",
            "name": "setPositionState",
            "slug": "API/MediaSession/setPositionState",
            "summary": "The MediaSession method setPositionState() is used to update the current document's media playback position and speed for presentation by user's device in any kind of interface that provides details about ongoing media.",
            "support": {
                "chrome": {
                    "version_added": "73"
                },
                "chrome_android": {
                    "version_added": "57"
                },
                "edge": {
                    "version_added": false
                },
                "firefox": [
                    {
                        "version_added": "82"
                    },
                    {
                        "version_added": "71",
                        "flags": [
                            {
                                "type": "preference",
                                "name": "dom.media.mediasession.enabled",
                                "value_to_set": "true"
                            }
                        ]
                    }
                ],
                "firefox_android": {
                    "version_added": "82",
                    "partial_implementation": true,
                    "notes": "Firefox exposes the API, but does not provide a corresponding user-facing media control interface."
                },
                "ie": {
                    "version_added": false
                },
                "opera": {
                    "version_added": true
                },
                "opera_android": {
                    "version_added": false
                },
                "safari": {
                    "version_added": false
                },
                "safari_ios": {
                    "version_added": false
                },
                "samsunginternet_android": {
                    "version_added": "7.0"
                },
                "webview_android": {
                    "version_added": false
                },
                "edge_blink": {
                    "version_added": "79"
                }
            },
            "title": "MediaSession.setPositionState()"
        }
    ],
    "the-mediasession-interface": [
        {
            "engines": [
                "blink",
                "gecko"
            ],
            "partial": [
                "gecko"
            ],
            "filename": "api/MediaSession.json",
            "name": "MediaSession",
            "slug": "API/MediaSession",
            "summary": "The MediaSession interface of the Media Session API allows a web page to provide custom behaviors for standard media playback interactions, and to report metadata that can be sent by the user agent to the device or operating system for presentation in standardized user interface elements.",
            "support": {
                "chrome": {
                    "version_added": "73"
                },
                "chrome_android": {
                    "version_added": "57"
                },
                "edge": {
                    "version_added": false
                },
                "firefox": [
                    {
                        "version_added": "82"
                    },
                    {
                        "version_added": "71",
                        "flags": [
                            {
                                "type": "preference",
                                "name": "dom.media.mediasession.enabled",
                                "value_to_set": "true"
                            }
                        ]
                    }
                ],
                "firefox_android": {
                    "version_added": "82",
                    "partial_implementation": true,
                    "notes": "Firefox exposes the API, but does not provide a corresponding user-facing media control interface."
                },
                "ie": {
                    "version_added": false
                },
                "opera": {
                    "version_added": true
                },
                "opera_android": {
                    "version_added": false
                },
                "safari": {
                    "version_added": false
                },
                "safari_ios": {
                    "version_added": false
                },
                "samsunginternet_android": {
                    "version_added": "7.0"
                },
                "webview_android": {
                    "version_added": false
                },
                "edge_blink": {
                    "version_added": "79"
                }
            },
            "title": "MediaSession"
        }
    ],
    "enumdef-mediasessionaction": [
        {
            "engines": [
                "blink",
                "gecko"
            ],
            "partial": [
                "gecko"
            ],
            "filename": "api/MediaSessionAction.json",
            "name": "MediaSessionAction",
            "slug": "API/MediaSessionAction",
            "summary": "The specific type of media session action to be handled on a MediaSession is identified using a string from the MediaSessionAction enumerated type.",
            "support": {
                "chrome": {
                    "version_added": "73"
                },
                "chrome_android": {
                    "version_added": "57"
                },
                "edge": {
                    "version_added": false
                },
                "firefox": [
                    {
                        "version_added": "82"
                    },
                    {
                        "version_added": "71",
                        "flags": [
                            {
                                "type": "preference",
                                "name": "dom.media.mediasession.enabled",
                                "value_to_set": "true"
                            }
                        ]
                    }
                ],
                "firefox_android": {
                    "version_added": "82",
                    "partial_implementation": true,
                    "notes": "Firefox exposes the API, but does not provide a corresponding user-facing media control interface."
                },
                "ie": {
                    "version_added": null
                },
                "opera": {
                    "version_added": false
                },
                "opera_android": {
                    "version_added": false
                },
                "safari": {
                    "version_added": false
                },
                "safari_ios": {
                    "version_added": false
                },
                "samsunginternet_android": {
                    "version_added": "7.0"
                },
                "webview_android": {
                    "version_added": false
                },
                "edge_blink": {
                    "version_added": "79"
                }
            },
            "title": "Media Session action types"
        }
    ],
    "dom-mediasessionactiondetails-action": [
        {
            "engines": [
                "blink",
                "gecko"
            ],
            "partial": [
                "gecko"
            ],
            "filename": "api/MediaSessionActionDetails.json",
            "name": "action",
            "slug": "API/MediaSessionActionDetails/action",
            "summary": "The action property is the only required property MediaSessionActionDetails dictionary, specifying the type of media session action which the action handler callback is being executed for.",
            "support": {
                "chrome": {
                    "version_added": "73"
                },
                "chrome_android": {
                    "version_added": "57"
                },
                "edge": {
                    "version_added": false
                },
                "firefox": [
                    {
                        "version_added": "82"
                    },
                    {
                        "version_added": "71",
                        "flags": [
                            {
                                "type": "preference",
                                "name": "dom.media.mediasession.enabled",
                                "value_to_set": "true"
                            }
                        ]
                    }
                ],
                "firefox_android": {
                    "version_added": "82",
                    "partial_implementation": true,
                    "notes": "Firefox exposes the API, but does not provide a corresponding user-facing media control interface."
                },
                "ie": {
                    "version_added": null
                },
                "opera": {
                    "version_added": false
                },
                "opera_android": {
                    "version_added": false
                },
                "safari": {
                    "version_added": false
                },
                "safari_ios": {
                    "version_added": false
                },
                "samsunginternet_android": {
                    "version_added": "7.0"
                },
                "webview_android": {
                    "version_added": false
                },
                "edge_blink": {
                    "version_added": "79"
                }
            },
            "title": "MediaSessionActionDetails.action"
        }
    ],
    "dom-mediasessionactiondetails-fastseek": [
        {
            "engines": [
                "blink"
            ],
            "filename": "api/MediaSessionActionDetails.json",
            "name": "fastSeek",
            "slug": "API/MediaSessionActionDetails/fastSeek",
            "summary": "The Boolean property fastSeek in the MediaSessionActionDetails dictionary is an optional value which, when specified and true, indicates that the requested seekto operation is part of an ongoing series of seekto operations. Your handler should take steps to return as quickly as possible by skipping any steps of its operation which are only necessary when the seek operation is complete.",
            "support": {
                "chrome": {
                    "version_added": "73"
                },
                "chrome_android": {
                    "version_added": "57"
                },
                "edge": {
                    "version_added": false
                },
                "firefox": {
                    "version_added": false
                },
                "firefox_android": {
                    "version_added": false
                },
                "ie": {
                    "version_added": null
                },
                "opera": {
                    "version_added": false
                },
                "opera_android": {
                    "version_added": false
                },
                "safari": {
                    "version_added": false
                },
                "safari_ios": {
                    "version_added": false
                },
                "samsunginternet_android": {
                    "version_added": "7.0"
                },
                "webview_android": {
                    "version_added": false
                },
                "edge_blink": {
                    "version_added": "79"
                }
            },
            "title": "MediaSessionActionDetails.fastSeek"
        }
    ],
    "dom-mediasessionactiondetails-seekoffset": [
        {
            "engines": [
                "blink",
                "gecko"
            ],
            "partial": [
                "gecko"
            ],
            "filename": "api/MediaSessionActionDetails.json",
            "name": "seekOffset",
            "slug": "API/MediaSessionActionDetails/seekOffset",
            "summary": "The MediaSessionActionDetails dictionary's seekOffset property is an optional value passed into the action handler callback to provide the number of seconds the seekforward and seekbackward actions should move the playback time by.",
            "support": {
                "chrome": {
                    "version_added": "73"
                },
                "chrome_android": {
                    "version_added": "57"
                },
                "edge": {
                    "version_added": false
                },
                "firefox": [
                    {
                        "version_added": "82"
                    },
                    {
                        "version_added": "71",
                        "flags": [
                            {
                                "type": "preference",
                                "name": "dom.media.mediasession.enabled",
                                "value_to_set": "true"
                            }
                        ]
                    }
                ],
                "firefox_android": {
                    "version_added": "82",
                    "partial_implementation": true,
                    "notes": "Firefox exposes the API, but does not provide a corresponding user-facing media control interface."
                },
                "ie": {
                    "version_added": null
                },
                "opera": {
                    "version_added": false
                },
                "opera_android": {
                    "version_added": false
                },
                "safari": {
                    "version_added": false
                },
                "safari_ios": {
                    "version_added": false
                },
                "samsunginternet_android": {
                    "version_added": "7.0"
                },
                "webview_android": {
                    "version_added": false
                },
                "edge_blink": {
                    "version_added": "79"
                }
            },
            "title": "MediaSessionActionDetails.seekOffset"
        }
    ],
    "dom-mediasessionactiondetails-seektime": [
        {
            "engines": [
                "blink"
            ],
            "filename": "api/MediaSessionActionDetails.json",
            "name": "seekTime",
            "slug": "API/MediaSessionActionDetails/seekTime",
            "summary": "The MediaSessionActionDetails dictionary's seekTime property is always included when a seekto action is sent to the action handler callback. Its value is the absolute time, in seconds, to move the current play position to.",
            "support": {
                "chrome": {
                    "version_added": "73"
                },
                "chrome_android": {
                    "version_added": "57"
                },
                "edge": {
                    "version_added": false
                },
                "firefox": {
                    "version_added": false
                },
                "firefox_android": {
                    "version_added": false
                },
                "ie": {
                    "version_added": null
                },
                "opera": {
                    "version_added": false
                },
                "opera_android": {
                    "version_added": false
                },
                "safari": {
                    "version_added": false
                },
                "safari_ios": {
                    "version_added": false
                },
                "samsunginternet_android": {
                    "version_added": "7.0"
                },
                "webview_android": {
                    "version_added": false
                },
                "edge_blink": {
                    "version_added": "79"
                }
            },
            "title": "MediaSessionActionDetails.seekTime"
        }
    ],
    "dictdef-mediasessionactiondetails": [
        {
            "engines": [
                "blink",
                "gecko"
            ],
            "partial": [
                "gecko"
            ],
            "filename": "api/MediaSessionActionDetails.json",
            "name": "MediaSessionActionDetails",
            "slug": "API/MediaSessionActionDetails",
            "summary": "The Media Session API's MediaSessionActionDetails dictionary is the type used by the sole input parameter into the callback which is executed when a media session action occurs.",
            "support": {
                "chrome": {
                    "version_added": "73"
                },
                "chrome_android": {
                    "version_added": "57"
                },
                "edge": {
                    "version_added": false
                },
                "firefox": [
                    {
                        "version_added": "82"
                    },
                    {
                        "version_added": "71",
                        "flags": [
                            {
                                "type": "preference",
                                "name": "dom.media.mediasession.enabled",
                                "value_to_set": "true"
                            }
                        ]
                    }
                ],
                "firefox_android": {
                    "version_added": "82",
                    "partial_implementation": true,
                    "notes": "Firefox exposes the API, but does not provide a corresponding user-facing media control interface."
                },
                "ie": {
                    "version_added": null
                },
                "opera": {
                    "version_added": false
                },
                "opera_android": {
                    "version_added": false
                },
                "safari": {
                    "version_added": false
                },
                "safari_ios": {
                    "version_added": false
                },
                "samsunginternet_android": {
                    "version_added": "7.0"
                },
                "webview_android": {
                    "version_added": false
                },
                "edge_blink": {
                    "version_added": "79"
                }
            },
            "title": "MediaSessionActionDetails"
        }
    ],
    "dom-navigator-mediasession": [
        {
            "engines": [
                "blink",
                "gecko"
            ],
            "filename": "api/Navigator.json",
            "name": "mediaSession",
            "slug": "API/Navigator/mediaSession",
            "summary": "The read-only Navigator property mediaSession returns a MediaSession object that can be used to share with the browser metadata and other information about the current playback state of media being handled by a document.",
            "support": {
                "chrome": {
                    "version_added": "73"
                },
                "chrome_android": {
                    "version_added": "57"
                },
                "edge": {
                    "version_added": false
                },
                "firefox": [
                    {
                        "version_added": "82"
                    },
                    {
                        "version_added": "71",
                        "flags": [
                            {
                                "type": "preference",
                                "name": "dom.media.mediasession.enabled",
                                "value_to_set": "true"
                            }
                        ]
                    }
                ],
                "firefox_android": {
                    "version_added": "82"
                },
                "ie": {
                    "version_added": false
                },
                "opera": {
                    "version_added": false
                },
                "opera_android": {
                    "version_added": false
                },
                "safari": {
                    "version_added": false
                },
                "safari_ios": {
                    "version_added": false
                },
                "samsunginternet_android": {
                    "version_added": "7.0"
                },
                "webview_android": {
                    "version_added": false
                },
                "edge_blink": {
                    "version_added": "79"
                }
            },
            "title": "Navigator.mediaSession"
        }
    ]
}
