{
    "dom-performance-clearresourcetimings": [
        {
            "engines": [
                "blink",
                "gecko",
                "webkit"
            ],
            "filename": "api/Performance.json",
            "name": "clearResourceTimings",
            "slug": "API/Performance/clearResourceTimings",
            "summary": "The clearResourceTimings() method removes all performance entries with an entryType of \"resource\" from the browser's performance data buffer and sets the size of the performance data buffer to zero. To set the size of the browser's performance data buffer, use the Performance.setResourceTimingBufferSize() method.",
            "support": {
                "chrome": [
                    {
                        "version_added": "46"
                    },
                    {
                        "version_added": "22",
                        "version_removed": "57",
                        "prefix": "webkit"
                    }
                ],
                "chrome_android": [
                    {
                        "version_added": "46"
                    },
                    {
                        "version_added": "25",
                        "version_removed": "57",
                        "prefix": "webkit"
                    }
                ],
                "edge": {
                    "version_added": "12"
                },
                "firefox": {
                    "version_added": "35"
                },
                "firefox_android": {
                    "version_added": "35"
                },
                "ie": {
                    "version_added": "10"
                },
                "nodejs": {
                    "version_added": false
                },
                "opera": {
                    "version_added": true
                },
                "opera_android": {
                    "version_added": true
                },
                "safari": {
                    "version_added": "11"
                },
                "safari_ios": {
                    "version_added": "11"
                },
                "samsunginternet_android": [
                    {
                        "version_added": "5.0"
                    },
                    {
                        "prefix": "webkit",
                        "version_added": "1.5",
                        "version_removed": "7.0"
                    }
                ],
                "webview_android": [
                    {
                        "version_added": "46"
                    },
                    {
                        "version_added": true,
                        "version_removed": "57",
                        "prefix": "webkit"
                    }
                ],
                "edge_blink": [
                    {
                        "version_added": "79"
                    },
                    {
                        "version_added": false,
                        "version_removed": "57",
                        "prefix": "webkit"
                    }
                ]
            },
            "title": "performance.clearResourceTimings()"
        }
    ],
    "dom-performance-onresourcetimingbufferfull": [
        {
            "engines": [
                "blink",
                "gecko",
                "webkit"
            ],
            "filename": "api/Performance.json",
            "name": "onresourcetimingbufferfull",
            "slug": "API/Performance/onresourcetimingbufferfull",
            "summary": "The onresourcetimingbufferfull property is an event handler that will be called when the resourcetimingbufferfull event is fired. This event is fired when the browser's resource timing performance buffer is full.",
            "support": {
                "chrome": [
                    {
                        "version_added": "46"
                    },
                    {
                        "version_added": "22",
                        "version_removed": "57",
                        "alternative_name": "onwebkitresourcetimingbufferfull"
                    }
                ],
                "chrome_android": [
                    {
                        "version_added": "46"
                    },
                    {
                        "version_added": "25",
                        "version_removed": "57",
                        "alternative_name": "onwebkitresourcetimingbufferfull"
                    }
                ],
                "edge": {
                    "version_added": false
                },
                "firefox": {
                    "version_added": "35"
                },
                "firefox_android": {
                    "version_added": "35"
                },
                "ie": {
                    "version_added": false
                },
                "nodejs": {
                    "version_added": false
                },
                "opera": {
                    "version_added": false
                },
                "opera_android": {
                    "version_added": true
                },
                "safari": {
                    "version_added": "11"
                },
                "safari_ios": {
                    "version_added": false
                },
                "samsunginternet_android": [
                    {
                        "version_added": "5.0"
                    },
                    {
                        "alternative_name": "onwebkitresourcetimingbufferfull",
                        "version_added": "1.5",
                        "version_removed": "7.0"
                    }
                ],
                "webview_android": [
                    {
                        "version_added": "46"
                    },
                    {
                        "version_added": true,
                        "version_removed": "57",
                        "alternative_name": "onwebkitresourcetimingbufferfull"
                    }
                ],
                "edge_blink": [
                    {
                        "version_added": "79"
                    },
                    {
                        "version_added": false,
                        "version_removed": "57",
                        "alternative_name": "onwebkitresourcetimingbufferfull"
                    }
                ]
            },
            "title": "Performance.onresourcetimingbufferfull"
        },
        {
            "engines": [
                "blink",
                "gecko",
                "webkit"
            ],
            "filename": "api/Performance.json",
            "name": "resourcetimingbufferfull_event",
            "slug": "API/Performance/resourcetimingbufferfull_event",
            "summary": "The resourcetimingbufferfull event is fired when the browser's resource timing buffer is full.",
            "support": {
                "chrome": [
                    {
                        "version_added": "46"
                    },
                    {
                        "version_added": "22",
                        "version_removed": "57",
                        "alternative_name": "webkitresourcetimingbufferfull"
                    }
                ],
                "chrome_android": [
                    {
                        "version_added": "46"
                    },
                    {
                        "version_added": "25",
                        "version_removed": "57",
                        "alternative_name": "webkitresourcetimingbufferfull"
                    }
                ],
                "edge": {
                    "version_added": false
                },
                "firefox": {
                    "version_added": true
                },
                "firefox_android": {
                    "version_added": true
                },
                "ie": {
                    "version_added": false
                },
                "nodejs": {
                    "version_added": false
                },
                "opera": {
                    "version_added": false
                },
                "opera_android": {
                    "version_added": true
                },
                "safari": {
                    "version_added": "11"
                },
                "safari_ios": {
                    "version_added": false
                },
                "samsunginternet_android": [
                    {
                        "version_added": "5.0"
                    },
                    {
                        "alternative_name": "webkitresourcetimingbufferfull",
                        "version_added": "1.5",
                        "version_removed": "7.0"
                    }
                ],
                "webview_android": [
                    {
                        "version_added": "46"
                    },
                    {
                        "version_added": true,
                        "version_removed": "57",
                        "alternative_name": "webkitresourcetimingbufferfull"
                    }
                ],
                "edge_blink": [
                    {
                        "version_added": "79"
                    },
                    {
                        "version_added": false,
                        "version_removed": "57",
                        "alternative_name": "webkitresourcetimingbufferfull"
                    }
                ]
            },
            "title": "Performance: resourcetimingbufferfull event"
        }
    ],
    "dom-performance-setresourcetimingbuffersize": [
        {
            "engines": [
                "blink",
                "gecko",
                "webkit"
            ],
            "filename": "api/Performance.json",
            "name": "setResourceTimingBufferSize",
            "slug": "API/Performance/setResourceTimingBufferSize",
            "summary": "The setResourceTimingBufferSize() method sets the browser's resource timing buffer size to the specified number of \"resource\" performance entry type objects.",
            "support": {
                "chrome": [
                    {
                        "version_added": "46"
                    },
                    {
                        "version_added": "22",
                        "version_removed": "57",
                        "prefix": "webkit"
                    }
                ],
                "chrome_android": [
                    {
                        "version_added": "46"
                    },
                    {
                        "version_added": "25",
                        "version_removed": "57",
                        "prefix": "webkit"
                    }
                ],
                "edge": {
                    "version_added": "12"
                },
                "firefox": {
                    "version_added": "35"
                },
                "firefox_android": {
                    "version_added": "35"
                },
                "ie": {
                    "version_added": "10"
                },
                "nodejs": {
                    "version_added": false
                },
                "opera": {
                    "version_added": true
                },
                "opera_android": {
                    "version_added": true
                },
                "safari": {
                    "version_added": "11"
                },
                "safari_ios": {
                    "version_added": false
                },
                "samsunginternet_android": [
                    {
                        "version_added": "5.0"
                    },
                    {
                        "prefix": "webkit",
                        "version_added": "1.5",
                        "version_removed": "7.0"
                    }
                ],
                "webview_android": [
                    {
                        "version_added": "46"
                    },
                    {
                        "version_added": true,
                        "version_removed": "57",
                        "prefix": "webkit"
                    }
                ],
                "edge_blink": [
                    {
                        "version_added": "79"
                    },
                    {
                        "version_added": false,
                        "version_removed": "57",
                        "prefix": "webkit"
                    }
                ]
            },
            "title": "performance.setResourceTimingBufferSize()"
        }
    ],
    "extensions-performance-interface": [
        {
            "engines": [
                "blink",
                "gecko",
                "webkit"
            ],
            "filename": "api/Performance.json",
            "name": "Performance",
            "slug": "API/Performance",
            "summary": "The Performance interface provides access to performance-related information for the current page. It's part of the High Resolution Time API, but is enhanced by the Performance Timeline API, the Navigation Timing API, the User Timing API, and the Resource Timing API.",
            "support": {
                "chrome": {
                    "version_added": "6"
                },
                "chrome_android": {
                    "version_added": "18"
                },
                "edge": {
                    "version_added": "12"
                },
                "firefox": {
                    "version_added": "7"
                },
                "firefox_android": {
                    "version_added": "7"
                },
                "ie": {
                    "version_added": "9"
                },
                "nodejs": {
                    "version_added": "8.5.0",
                    "notes": [
                        "Stability: Experimental",
                        "Exported from the <code>perf_hooks</code> module"
                    ],
                    "partial_implementation": true
                },
                "opera": {
                    "version_added": "15"
                },
                "opera_android": {
                    "version_added": "14"
                },
                "safari": {
                    "version_added": "8"
                },
                "safari_ios": {
                    "version_added": "9"
                },
                "samsunginternet_android": {
                    "version_added": "1.0"
                },
                "webview_android": {
                    "version_added": "1"
                },
                "edge_blink": {
                    "version_added": "79"
                }
            },
            "title": "Performance"
        }
    ],
    "dom-performanceresourcetiming-connectend": [
        {
            "engines": [
                "blink",
                "gecko",
                "webkit"
            ],
            "filename": "api/PerformanceResourceTiming.json",
            "name": "connectEnd",
            "slug": "API/PerformanceResourceTiming/connectEnd",
            "summary": "The connectEnd read-only property returns the timestamp immediately after the browser finishes establishing the connection to the server to retrieve the resource. The timestamp value includes the time interval to establish the transport connection, as well as other time intervals such as SSL handshake and SOCKS authentication.",
            "support": {
                "chrome": {
                    "version_added": "43"
                },
                "chrome_android": {
                    "version_added": "43"
                },
                "edge": {
                    "version_added": "12"
                },
                "firefox": {
                    "version_added": "40"
                },
                "firefox_android": {
                    "version_added": "42"
                },
                "ie": {
                    "version_added": "10"
                },
                "opera": {
                    "version_added": "32"
                },
                "opera_android": {
                    "version_added": "32"
                },
                "safari": {
                    "version_added": "11"
                },
                "safari_ios": {
                    "version_added": "11"
                },
                "samsunginternet_android": {
                    "version_added": "4.0"
                },
                "webview_android": {
                    "version_added": "43"
                },
                "edge_blink": {
                    "version_added": "79"
                }
            },
            "title": "PerformanceResourceTiming.connectEnd"
        }
    ],
    "dom-performanceresourcetiming-connectstart": [
        {
            "engines": [
                "blink",
                "gecko",
                "webkit"
            ],
            "filename": "api/PerformanceResourceTiming.json",
            "name": "connectStart",
            "slug": "API/PerformanceResourceTiming/connectStart",
            "summary": "The connectStart read-only property returns the timestamp immediately before the user agent starts establishing the connection to the server to retrieve the resource.",
            "support": {
                "chrome": {
                    "version_added": "43"
                },
                "chrome_android": {
                    "version_added": "43"
                },
                "edge": {
                    "version_added": "12"
                },
                "firefox": {
                    "version_added": "40"
                },
                "firefox_android": {
                    "version_added": "42"
                },
                "ie": {
                    "version_added": "10"
                },
                "opera": {
                    "version_added": "32"
                },
                "opera_android": {
                    "version_added": "32"
                },
                "safari": {
                    "version_added": "11"
                },
                "safari_ios": {
                    "version_added": "11"
                },
                "samsunginternet_android": {
                    "version_added": "4.0"
                },
                "webview_android": {
                    "version_added": "43"
                },
                "edge_blink": {
                    "version_added": "79"
                }
            },
            "title": "PerformanceResourceTiming.connectStart"
        }
    ],
    "dom-performanceresourcetiming-domainlookupend": [
        {
            "engines": [
                "blink",
                "gecko",
                "webkit"
            ],
            "filename": "api/PerformanceResourceTiming.json",
            "name": "domainLookupEnd",
            "slug": "API/PerformanceResourceTiming/domainLookupEnd",
            "summary": "The domainLookupEnd read-only property returns the timestamp immediately after the browser finishes the domain name lookup for the resource.",
            "support": {
                "chrome": {
                    "version_added": "43"
                },
                "chrome_android": {
                    "version_added": "43"
                },
                "edge": {
                    "version_added": "12"
                },
                "firefox": {
                    "version_added": "40"
                },
                "firefox_android": {
                    "version_added": "42"
                },
                "ie": {
                    "version_added": false
                },
                "opera": {
                    "version_added": "30"
                },
                "opera_android": {
                    "version_added": "30"
                },
                "safari": {
                    "version_added": "11"
                },
                "safari_ios": {
                    "version_added": "11"
                },
                "samsunginternet_android": {
                    "version_added": "4.0"
                },
                "webview_android": {
                    "version_added": "43"
                },
                "edge_blink": {
                    "version_added": "79"
                }
            },
            "title": "PerformanceResourceTiming.domainLookupEnd"
        }
    ],
    "dom-performanceresourcetiming-domainlookupstart": [
        {
            "engines": [
                "blink",
                "gecko",
                "webkit"
            ],
            "filename": "api/PerformanceResourceTiming.json",
            "name": "domainLookupStart",
            "slug": "API/PerformanceResourceTiming/domainLookupStart",
            "summary": "The domainLookupStart read-only property returns the timestamp immediately before the browser starts the domain name lookup for the resource.",
            "support": {
                "chrome": {
                    "version_added": "43"
                },
                "chrome_android": {
                    "version_added": "43"
                },
                "edge": {
                    "version_added": "12"
                },
                "firefox": {
                    "version_added": "40"
                },
                "firefox_android": {
                    "version_added": "42"
                },
                "ie": {
                    "version_added": false
                },
                "opera": {
                    "version_added": "30"
                },
                "opera_android": {
                    "version_added": "30"
                },
                "safari": {
                    "version_added": "11"
                },
                "safari_ios": {
                    "version_added": "11"
                },
                "samsunginternet_android": {
                    "version_added": "4.0"
                },
                "webview_android": {
                    "version_added": "43"
                },
                "edge_blink": {
                    "version_added": "79"
                }
            },
            "title": "PerformanceResourceTiming.domainLookupStart"
        }
    ],
    "dom-performanceresourcetiming-fetchstart": [
        {
            "engines": [
                "blink",
                "gecko",
                "webkit"
            ],
            "filename": "api/PerformanceResourceTiming.json",
            "name": "fetchStart",
            "slug": "API/PerformanceResourceTiming/fetchStart",
            "summary": "The fetchStart read-only property represents a timestamp immediately before the browser starts to fetch the resource.",
            "support": {
                "chrome": {
                    "version_added": "43"
                },
                "chrome_android": {
                    "version_added": "43"
                },
                "edge": {
                    "version_added": "12"
                },
                "firefox": {
                    "version_added": "40"
                },
                "firefox_android": {
                    "version_added": "42"
                },
                "ie": {
                    "version_added": false
                },
                "opera": {
                    "version_added": "30"
                },
                "opera_android": {
                    "version_added": "30"
                },
                "safari": {
                    "version_added": "11"
                },
                "safari_ios": {
                    "version_added": "11"
                },
                "samsunginternet_android": {
                    "version_added": "4.0"
                },
                "webview_android": {
                    "version_added": "43"
                },
                "edge_blink": {
                    "version_added": "79"
                }
            },
            "title": "PerformanceResourceTiming.fetchStart"
        }
    ],
    "dom-performanceresourcetiming-initiatortype": [
        {
            "engines": [
                "blink",
                "gecko",
                "webkit"
            ],
            "filename": "api/PerformanceResourceTiming.json",
            "name": "initiatorType",
            "slug": "API/PerformanceResourceTiming/initiatorType",
            "summary": "The initiatorType read-only property is a string that represents the type of resource that initiated the performance event.",
            "support": {
                "chrome": {
                    "version_added": "43"
                },
                "chrome_android": {
                    "version_added": "43"
                },
                "edge": {
                    "version_added": "12"
                },
                "firefox": {
                    "version_added": "40"
                },
                "firefox_android": {
                    "version_added": "42"
                },
                "ie": {
                    "version_added": false
                },
                "opera": {
                    "version_added": "30"
                },
                "opera_android": {
                    "version_added": "30"
                },
                "safari": {
                    "version_added": "11"
                },
                "safari_ios": {
                    "version_added": "11"
                },
                "samsunginternet_android": {
                    "version_added": "4.0"
                },
                "webview_android": {
                    "version_added": "43"
                },
                "edge_blink": {
                    "version_added": "79"
                }
            },
            "title": "PerformanceResourceTiming.initiatorType"
        }
    ],
    "dom-performanceresourcetiming-redirectend": [
        {
            "engines": [
                "blink",
                "gecko",
                "webkit"
            ],
            "filename": "api/PerformanceResourceTiming.json",
            "name": "redirectEnd",
            "slug": "API/PerformanceResourceTiming/redirectEnd",
            "summary": "The redirectEnd read-only property returns a timestamp immediately after receiving the last byte of the response of the last redirect.",
            "support": {
                "chrome": {
                    "version_added": "43"
                },
                "chrome_android": {
                    "version_added": "43"
                },
                "edge": {
                    "version_added": "12"
                },
                "firefox": {
                    "version_added": "40"
                },
                "firefox_android": {
                    "version_added": "42"
                },
                "ie": {
                    "version_added": false
                },
                "opera": {
                    "version_added": "30"
                },
                "opera_android": {
                    "version_added": "30"
                },
                "safari": {
                    "version_added": "11"
                },
                "safari_ios": {
                    "version_added": "11"
                },
                "samsunginternet_android": {
                    "version_added": "4.0"
                },
                "webview_android": {
                    "version_added": "43"
                },
                "edge_blink": {
                    "version_added": "79"
                }
            },
            "title": "PerformanceResourceTiming.redirectEnd"
        }
    ],
    "dom-performanceresourcetiming-redirectstart": [
        {
            "engines": [
                "blink",
                "gecko",
                "webkit"
            ],
            "filename": "api/PerformanceResourceTiming.json",
            "name": "redirectStart",
            "slug": "API/PerformanceResourceTiming/redirectStart",
            "summary": "The redirectStart read-only property returns a timestamp representing the start time of the fetch which that initiates the redirect.",
            "support": {
                "chrome": {
                    "version_added": "43"
                },
                "chrome_android": {
                    "version_added": "43"
                },
                "edge": {
                    "version_added": "12"
                },
                "firefox": {
                    "version_added": "40"
                },
                "firefox_android": {
                    "version_added": "42"
                },
                "ie": {
                    "version_added": false
                },
                "opera": {
                    "version_added": "30"
                },
                "opera_android": {
                    "version_added": "30"
                },
                "safari": {
                    "version_added": "11"
                },
                "safari_ios": {
                    "version_added": "11"
                },
                "samsunginternet_android": {
                    "version_added": "4.0"
                },
                "webview_android": {
                    "version_added": "43"
                },
                "edge_blink": {
                    "version_added": "79"
                }
            },
            "title": "PerformanceResourceTiming.redirectStart"
        }
    ],
    "dom-performanceresourcetiming-requeststart": [
        {
            "engines": [
                "blink",
                "gecko",
                "webkit"
            ],
            "filename": "api/PerformanceResourceTiming.json",
            "name": "requestStart",
            "slug": "API/PerformanceResourceTiming/requestStart",
            "summary": "The requestStart read-only property returns a timestamp of the time immediately before the browser starts requesting the resource from the server, cache, or local resource. If the transport connection fails and the browser retires the request, the value returned will be the start of the retry request.",
            "support": {
                "chrome": {
                    "version_added": "43"
                },
                "chrome_android": {
                    "version_added": "43"
                },
                "edge": {
                    "version_added": "12"
                },
                "firefox": {
                    "version_added": "40"
                },
                "firefox_android": {
                    "version_added": "42"
                },
                "ie": {
                    "version_added": false
                },
                "opera": {
                    "version_added": "30"
                },
                "opera_android": {
                    "version_added": "30"
                },
                "safari": {
                    "version_added": "11"
                },
                "safari_ios": {
                    "version_added": "11"
                },
                "samsunginternet_android": {
                    "version_added": "4.0"
                },
                "webview_android": {
                    "version_added": "43"
                },
                "edge_blink": {
                    "version_added": "79"
                }
            },
            "title": "PerformanceResourceTiming.requestStart"
        }
    ],
    "dom-performanceresourcetiming-responseend": [
        {
            "engines": [
                "blink",
                "gecko",
                "webkit"
            ],
            "filename": "api/PerformanceResourceTiming.json",
            "name": "responseEnd",
            "slug": "API/PerformanceResourceTiming/responseEnd",
            "summary": "The responseEnd read-only property returns a timestamp immediately after the browser receives the last byte of the resource or immediately before the transport connection is closed, whichever comes first.",
            "support": {
                "chrome": {
                    "version_added": "43"
                },
                "chrome_android": {
                    "version_added": "43"
                },
                "edge": {
                    "version_added": "12"
                },
                "firefox": {
                    "version_added": "40"
                },
                "firefox_android": {
                    "version_added": "42"
                },
                "ie": {
                    "version_added": false
                },
                "opera": {
                    "version_added": "30"
                },
                "opera_android": {
                    "version_added": "30"
                },
                "safari": {
                    "version_added": "11"
                },
                "safari_ios": {
                    "version_added": "11"
                },
                "samsunginternet_android": {
                    "version_added": "4.0"
                },
                "webview_android": {
                    "version_added": "43"
                },
                "edge_blink": {
                    "version_added": "79"
                }
            },
            "title": "PerformanceResourceTiming.responseEnd"
        }
    ],
    "dom-performanceresourcetiming-responsestart": [
        {
            "engines": [
                "blink",
                "gecko",
                "webkit"
            ],
            "filename": "api/PerformanceResourceTiming.json",
            "name": "responseStart",
            "slug": "API/PerformanceResourceTiming/responseStart",
            "summary": "The responseStart read-only property returns a timestamp immediately after the browser receives the first byte of the response from the server, cache, or local resource.",
            "support": {
                "chrome": {
                    "version_added": "43"
                },
                "chrome_android": {
                    "version_added": "43"
                },
                "edge": {
                    "version_added": "12"
                },
                "firefox": {
                    "version_added": "40"
                },
                "firefox_android": {
                    "version_added": "42"
                },
                "ie": {
                    "version_added": false
                },
                "opera": {
                    "version_added": "30"
                },
                "opera_android": {
                    "version_added": "30"
                },
                "safari": {
                    "version_added": "11"
                },
                "safari_ios": {
                    "version_added": "11"
                },
                "samsunginternet_android": {
                    "version_added": "4.0"
                },
                "webview_android": {
                    "version_added": "43"
                },
                "edge_blink": {
                    "version_added": "79"
                }
            },
            "title": "PerformanceResourceTiming.responseStart"
        }
    ],
    "dom-performanceresourcetiming-secureconnectionstart": [
        {
            "engines": [
                "blink",
                "gecko",
                "webkit"
            ],
            "filename": "api/PerformanceResourceTiming.json",
            "name": "secureConnectionStart",
            "slug": "API/PerformanceResourceTiming/secureConnectionStart",
            "summary": "The secureConnectionStart read-only property returns a timestamp immediately before the browser starts the handshake process to secure the current connection. If a secure connection is not used, the property returns zero.",
            "support": {
                "chrome": {
                    "version_added": "43"
                },
                "chrome_android": {
                    "version_added": "43"
                },
                "edge": {
                    "version_added": "18"
                },
                "firefox": {
                    "version_added": "40"
                },
                "firefox_android": {
                    "version_added": "42"
                },
                "ie": {
                    "version_added": false
                },
                "opera": {
                    "version_added": "30"
                },
                "opera_android": {
                    "version_added": "30"
                },
                "safari": {
                    "version_added": "11"
                },
                "safari_ios": {
                    "version_added": "11"
                },
                "samsunginternet_android": {
                    "version_added": "4.0"
                },
                "webview_android": {
                    "version_added": "43"
                },
                "edge_blink": {
                    "version_added": "79"
                }
            },
            "title": "PerformanceResourceTiming.secureConnectionStart"
        }
    ],
    "performanceresourcetiming": [
        {
            "engines": [
                "blink",
                "gecko",
                "webkit"
            ],
            "filename": "api/PerformanceResourceTiming.json",
            "name": "PerformanceResourceTiming",
            "slug": "API/PerformanceResourceTiming",
            "summary": "The PerformanceResourceTiming interface enables retrieval and analysis of detailed network timing data regarding the loading of an application's resources. An application can use the timing metrics to determine, for example, the length of time it takes to fetch a specific resource, such as an XMLHttpRequest, <SVG>, image, or script.",
            "support": {
                "chrome": {
                    "version_added": "43"
                },
                "chrome_android": {
                    "version_added": "43"
                },
                "edge": {
                    "version_added": "12"
                },
                "firefox": {
                    "version_added": "40"
                },
                "firefox_android": {
                    "version_added": "42"
                },
                "ie": {
                    "version_added": "10"
                },
                "opera": {
                    "version_added": "30"
                },
                "opera_android": {
                    "version_added": "30"
                },
                "safari": {
                    "version_added": "11"
                },
                "safari_ios": {
                    "version_added": "11"
                },
                "samsunginternet_android": {
                    "version_added": "4.0"
                },
                "webview_android": {
                    "version_added": "43"
                },
                "edge_blink": {
                    "version_added": "79"
                }
            },
            "title": "PerformanceResourceTiming"
        }
    ]
}
